grail/__init__.py
grail/api.py
grail/app.py
grail/cli.py
grail/settings.yaml
grail/upload.py
grail/codegen/__init__.py
grail/codegen/application.py
grail/codegen/base.py
grail/codegen/diagram.py
grail/codegen/fab_app.py
grail/codegen/filesystem.py
grail/extensions/appbuilder.py
grail/extensions/avatar.py
grail/extensions/debugger.py
grail/extensions/endpoints.py
grail/extensions/gateway.py
grail/extensions/migrate.py
grail/extensions/openalchemy.py
grail/extensions/page_editor.py
grail/extensions/pages.py
grail/extensions/pgnotify.py
grail/extensions/settings.py
grail/extensions/shell2http.py
grail/extensions/signals.py
grail/extensions/uploads.py
grail/extensions/adr/__init__.py
grail/extensions/adr/cli.py
grail/extensions/adr/lib.py
grail/extensions/adr/templates/adr/adr.md
grail/extensions/adr/templates/adr/index.html
grail/extensions/auth/__init__.py
grail/extensions/auth/templates/auth/layout.html
grail/extensions/auth/templates/auth/sign-in.html
grail/extensions/auth/templates/auth/sign-up.html
grail/extensions/configuration/__init__.py
grail/extensions/configuration/base.py
grail/extensions/configuration/validators.py
grail/extensions/configuration/views.py
grail/extensions/generators/__init__.py
grail/extensions/generators/gen.py
grail/extensions/generators/templates/fabview.py.jinja2
grail/extensions/gpt/__init__.py
grail/extensions/gpt/coder.py
grail/extensions/grapesjs/__init__.py
grail/extensions/grapesjs/config.py
grail/extensions/grapesjs/model.py
grail/extensions/grapesjs/view.py
grail/extensions/grapesjs/static/grapesjs-preset-webpage.min.css
grail/extensions/grapesjs/static/grapesjs-preset-webpage.min.js
grail/extensions/grapesjs/templates/blocks/form1.html
grail/extensions/grapesjs/templates/blocks/form2.html
grail/extensions/grapesjs/templates/grapesjs/editor.js
grail/extensions/grapesjs/templates/grapesjs/index.html
grail/extensions/grapesjs/templates/grapesjs/index2.html
grail/extensions/grapesjs/templates/grapesjs/preview.html
grail_app-0.0.0.dist-info/LICENSE.txt
grail_app-0.0.0.dist-info/METADATA
grail_app-0.0.0.dist-info/WHEEL
grail_app-0.0.0.dist-info/entry_points.txt
grail_app-0.0.0.dist-info/top_level.txt
grail_app-0.0.0.dist-info/RECORD
