Metadata-Version: 2.1
Name: grail-app
Version: 0.0.0
Summary: Grail is a low-code framework for building Flask-based web applications.
Author: Lakeshore Labs
License: The MIT License (MIT)
Project-URL: Home, http://gitlab.com/lakeshorelabs/grail
Classifier: License :: OSI Approved :: MIT License
Requires-Python: >=3.9
License-File: LICENSE.txt
Requires-Dist: annotated-types ==0.5.0
Requires-Dist: attrs ==23.1.0
Requires-Dist: beautifulsoup4 ==4.12.2
Requires-Dist: blinker ==1.6.2
Requires-Dist: cairocffi ==1.6.1
Requires-Dist: CairoSVG ==2.7.1
Requires-Dist: certifi ==2023.7.22
Requires-Dist: cffi ==1.16.0
Requires-Dist: charset-normalizer ==3.2.0
Requires-Dist: click ==8.1.6
Requires-Dist: cssselect2 ==0.7.0
Requires-Dist: defusedxml ==0.7.1
Requires-Dist: dynaconf ==3.2.3
Requires-Dist: Flask ==2.3.3
Requires-Dist: Flask-DebugToolbar ==0.13.1
Requires-Dist: Flask-Executor ==1.0.0
Requires-Dist: Flask-FlatPages ==0.8.1
Requires-Dist: flask-htmx ==0.3.1
Requires-Dist: Flask-Shell2HTTP ==1.9.1
Requires-Dist: idna ==3.4
Requires-Dist: itsdangerous ==2.1.2
Requires-Dist: Jinja2 ==3.1.2
Requires-Dist: Markdown ==3.4.4
Requires-Dist: MarkupSafe ==2.1.3
Requires-Dist: packaging ==23.1
Requires-Dist: Pillow ==10.0.0
Requires-Dist: py-avataaars ==1.1.2
Requires-Dist: pycparser ==2.21
Requires-Dist: pydantic ==1.10.13
Requires-Dist: pypgrest ==0.2.0
Requires-Dist: python-dotenv ==1.0.0
Requires-Dist: PyYAML ==6.0.1
Requires-Dist: requests ==2.31.0
Requires-Dist: ruamel.yaml ==0.17.32
Requires-Dist: ruamel.yaml.clib ==0.2.7
Requires-Dist: six ==1.16.0
Requires-Dist: soupsieve ==2.4.1
Requires-Dist: subclass-register ==1.0.1
Requires-Dist: tinycss2 ==1.2.1
Requires-Dist: typing-extensions ==4.7.1
Requires-Dist: unpoly ==0.4.0
Requires-Dist: urllib3 ==2.0.4
Requires-Dist: webencodings ==0.5.1
Requires-Dist: Werkzeug ==2.3.7
